projection/__init__.py
projection/functions.py
projection/main.py
projection/shared.cpython-311-darwin.so
projectionSVD-0.1.3.dist-info/LICENSE
projectionSVD-0.1.3.dist-info/METADATA
projectionSVD-0.1.3.dist-info/WHEEL
projectionSVD-0.1.3.dist-info/entry_points.txt
projectionSVD-0.1.3.dist-info/top_level.txt
projectionSVD-0.1.3.dist-info/RECORD
